{"pages_api_jd-modal-ref.md":"0f21be42","pages_guide_general-usage.md":"d5d26826","pages_guide_quick-started.md":"c4e8025f","pages_open-strategy_extend.md":"6ceb988f","pages_open-strategy_intro.md":"938df8a5","pages_packages_composables.md":"89bc0c1d","pages_api_jd-modal-service.md":"c061fb3f","index.md":"3a8bf67c","pages_practice_close.md":"96e04a7a","pages_practice_data-pass.md":"992e1896","pages_practice_design-entry-component.md":"e4382ebe","pages_practice_design-intro.md":"2848461e","pages_practice_design-open-strategy.md":"c1ca57b3","pages_practice_design-panel-style.md":"8730f91c","pages_practice_history-back.md":"ea2a149f","pages_packages_open-strategy.md":"4195d716","pages_practice_open.md":"59293d4a"}
