{"index.md":"Dtm6m99j","pages_api_jd-modal-ref.md":"CaBlTRFC","pages_api_jd-modal-service.md":"DiFE9M2M","pages_guide_general-usage.md":"CfuA-1DF","pages_guide_quick-started.md":"CJ05PU83","pages_open-strategy_extend.md":"B1HB9V4s","pages_open-strategy_intro.md":"B3tXOzDs","pages_packages_composables.md":"CPGnOTjI","pages_packages_open-strategy.md":"CxeuuIYY","pages_practice_close.md":"CFafJZsU","pages_practice_data-pass.md":"B3eUZITz","pages_practice_design-entry-component.md":"KNUipEhu","pages_practice_design-intro.md":"COYyIpZI","pages_practice_design-open-strategy.md":"CyFe58R-","pages_practice_design-panel-style.md":"DJrJauQe","pages_practice_history-back.md":"DoUMpBsa","pages_practice_open.md":"BzqACl7T","v2_api_jd-modal-ref.md":"DM4xH2iG","v2_api_jd-modal-service.md":"DWFaoR0d","v2_example_example-action-sheet.md":"6xb1OlHT","v2_example_example-close.md":"DeVLMk6M","v2_example_example-confirm.md":"CJ7U127H","v2_example_example-entry-component.md":"BLXjB4St","v2_example_example-open-startegy.md":"DFjVJDEo","v2_example_example-open.md":"7MVd9xAF","v2_example_example-use-before-leave.md":"BG3642iR","v2_example_example-use-focus-trap.md":"DEPEoQa_","v2_example_example-use-intercept-close.md":"BRD-MIG9","v2_example_example-use-pull-down-close.md":"pPH_2nBA","v2_guide_quick-started.md":"Cv91G00K","v2_guide_usage.md":"CYNwV_OV"}
