{"index.md":"Dtm6m99j","pages_api_jd-modal-ref.md":"CaBlTRFC","pages_api_jd-modal-service.md":"DiFE9M2M","pages_guide_general-usage.md":"CfuA-1DF","pages_guide_quick-started.md":"CJ05PU83","pages_open-strategy_extend.md":"B1HB9V4s","pages_open-strategy_intro.md":"B3tXOzDs","pages_packages_composables.md":"CPGnOTjI","pages_packages_open-strategy.md":"CxeuuIYY","pages_practice_close.md":"CFafJZsU","pages_practice_data-pass.md":"B3eUZITz","pages_practice_design-entry-component.md":"KNUipEhu","pages_practice_design-intro.md":"COYyIpZI","pages_practice_design-open-strategy.md":"CyFe58R-","pages_practice_design-panel-style.md":"DJrJauQe","pages_practice_history-back.md":"DoUMpBsa","pages_practice_open.md":"BzqACl7T","v2_api_jd-modal-ref.md":"DM4xH2iG","v2_api_jd-modal-service.md":"Bcp4mixU","v2_example_example-action-sheet.md":"yug5jeWE","v2_example_example-close.md":"RW3k5EzZ","v2_example_example-confirm.md":"BrXKvOht","v2_example_example-entry-component.md":"DNGa1Pbi","v2_example_example-open-startegy.md":"aoi0fOKe","v2_example_example-open.md":"B5gQwT2n","v2_example_example-use-before-leave.md":"DRgQmYFy","v2_example_example-use-focus-trap.md":"DYv2seQe","v2_example_example-use-intercept-close.md":"BnGX3v-4","v2_example_example-use-pull-down-close.md":"CFO99iO9","v2_guide_quick-started.md":"B1urs8bN","v2_guide_usage.md":"C64GsvZ2"}
